MintPy/__init__.py
MintPy/mintpy/__init__.py
MintPy/mintpy/add.py
MintPy/mintpy/add_attribute.py
MintPy/mintpy/asc_desc2horz_vert.py
MintPy/mintpy/correlation_with_dem.py
MintPy/mintpy/dem_error.py
MintPy/mintpy/dem_gsi.py
MintPy/mintpy/diff.py
MintPy/mintpy/generate_mask.py
MintPy/mintpy/geocode.py
MintPy/mintpy/ifgram_inversion.py
MintPy/mintpy/ifgram_reconstruction.py
MintPy/mintpy/image_math.py
MintPy/mintpy/incidence_angle.py
MintPy/mintpy/info.py
MintPy/mintpy/load_data.py
MintPy/mintpy/load_gbis.py
MintPy/mintpy/load_hdf5.py
MintPy/mintpy/local_oscilator_drift.py
MintPy/mintpy/lookup_geo2radar.py
MintPy/mintpy/mask.py
MintPy/mintpy/match.py
MintPy/mintpy/modify_network.py
MintPy/mintpy/multi_transect.py
MintPy/mintpy/multilook.py
MintPy/mintpy/plot_coherence_matrix.py
MintPy/mintpy/plot_network.py
MintPy/mintpy/plot_transection.py
MintPy/mintpy/prep_aria.py
MintPy/mintpy/prep_fringe.py
MintPy/mintpy/prep_gamma.py
MintPy/mintpy/prep_giant.py
MintPy/mintpy/prep_isce.py
MintPy/mintpy/prep_roipac.py
MintPy/mintpy/prep_snap.py
MintPy/mintpy/range_distance.py
MintPy/mintpy/reference_date.py
MintPy/mintpy/reference_point.py
MintPy/mintpy/remove_hdf5_dataset.py
MintPy/mintpy/remove_ramp.py
MintPy/mintpy/save_gbis.py
MintPy/mintpy/save_gdal.py
MintPy/mintpy/save_gmt.py
MintPy/mintpy/save_hdfeos5.py
MintPy/mintpy/save_ifg_list4giant.py
MintPy/mintpy/save_kmz.py
MintPy/mintpy/save_kmz_timeseries.py
MintPy/mintpy/save_qgis.py
MintPy/mintpy/save_roipac.py
MintPy/mintpy/select_network.py
MintPy/mintpy/smallbaselineApp.py
MintPy/mintpy/spatial_average.py
MintPy/mintpy/spatial_filter.py
MintPy/mintpy/subset.py
MintPy/mintpy/temporal_average.py
MintPy/mintpy/temporal_derivative.py
MintPy/mintpy/temporal_filter.py
MintPy/mintpy/timeseries2velocity.py
MintPy/mintpy/timeseries_rms.py
MintPy/mintpy/tropo_phase_elevation.py
MintPy/mintpy/tropo_pyaps.py
MintPy/mintpy/tropo_pyaps3.py
MintPy/mintpy/tsview.py
MintPy/mintpy/unwrap_error_bridging.py
mintpy_beta_meissam-0.0.1.dist-info/LICENSE
mintpy_beta_meissam-0.0.1.dist-info/METADATA
mintpy_beta_meissam-0.0.1.dist-info/WHEEL
mintpy_beta_meissam-0.0.1.dist-info/top_level.txt
mintpy_beta_meissam-0.0.1.dist-info/RECORD
