Metadata-Version: 2.1
Name: mintpy-beta-meissam
Version: 0.0.1
Summary: MintPy Beta Version
Home-page: https://github.com/mehdizadehm/MintPy
Author: Meissam Mehdizadeh
Author-email: meissam.mehdizadeh@gmail.com
License: UNKNOWN
Platform: UNKNOWN
Classifier: Programming Language :: Python :: 3
Classifier: License :: OSI Approved :: MIT License
Classifier: Operating System :: OS Independent
Requires-Python: >=3.6
